{"analytics_identifier":null,"base_path":"/government/1820-to-1826-tory-government","content_id":"0a64be42-43fb-44dd-81b5-ca869aacf5b0","document_type":"government","first_published_at":"2019-11-25T11:05:37.000+00:00","locale":"en","phase":"live","public_updated_at":"2019-11-25T11:05:27.000+00:00","publishing_app":"whitehall","publishing_scheduled_at":null,"rendering_app":"government-frontend","scheduled_publishing_delay_seconds":null,"schema_name":"government","title":"1820 to 1826 Tory government","updated_at":"2019-11-25T11:05:37.934Z","withdrawn_notice":{},"publishing_request_id":"9635-1574679937.702-10.3.3.1-429","links":{"available_translations":[{"title":"1820 to 1826 Tory government","public_updated_at":"2019-11-25T11:05:27Z","document_type":"government","schema_name":"government","base_path":"/government/1820-to-1826-tory-government","api_path":"/api/content/government/1820-to-1826-tory-government","withdrawn":false,"content_id":"0a64be42-43fb-44dd-81b5-ca869aacf5b0","locale":"en","api_url":"https://www.gov.uk/api/content/government/1820-to-1826-tory-government","web_url":"https://www.gov.uk/government/1820-to-1826-tory-government","links":{}}]},"description":null,"details":{"started_on":"1820-04-21T00:00:00+00:00","ended_on":"1826-07-24T00:00:00+00:00","current":false}}