{"analytics_identifier":null,"base_path":"/government/news/green-light-for-dashboards-in-2019-puts-pension-savers-in-the-driving-seat","content_id":"7d33a106-40f3-4309-b823-ad88e130623e","document_type":"press_release","first_published_at":"2019-04-04T12:40:46.000+00:00","locale":"en","phase":"live","public_updated_at":"2019-04-04T12:40:46.000+00:00","publishing_app":"content-publisher","publishing_scheduled_at":null,"rendering_app":"government-frontend","scheduled_publishing_delay_seconds":null,"schema_name":"news_article","title":"Green light for dashboards in 2019 puts pension savers in the driving seat","updated_at":"2019-11-21T11:36:00.181Z","withdrawn_notice":{},"publishing_request_id":"21025-1554381646.001-10.3.3.1-1362","links":{"taxons":[{"api_path":"/api/content/employment/working-state-pension","base_path":"/employment/working-state-pension","content_id":"f8b6d54b-cc94-4b32-aac4-8cd344087407","document_type":"taxon","locale":"en","public_updated_at":"2018-08-22T11:08:23Z","schema_name":"taxon","title":"State Pension","withdrawn":false,"description":"Calculating State Pension, Pension Credit, eligibility, claiming and deferring","details":{"internal_name":"State Pension [M]","notes_for_editors":"","visible_to_departmental_editors":false},"phase":"live","links":{"parent_taxons":[{"api_path":"/api/content/employment/working","base_path":"/employment/working","content_id":"092348a4-b896-4f8f-a0dc-e6d4605a4904","document_type":"taxon","locale":"en","public_updated_at":"2018-08-22T11:08:23Z","schema_name":"taxon","title":"Working, jobs and pensions","withdrawn":false,"description":"Includes holidays and finding a job","details":{"internal_name":"Working, jobs and pensions [M] (merged, level 2, work theme)","notes_for_editors":"","visible_to_departmental_editors":false},"phase":"live","links":{"parent_taxons":[{"api_path":"/api/content/work","base_path":"/work","content_id":"d0f1e5a3-c8f4-4780-8678-994f19104b21","document_type":"taxon","locale":"en","public_updated_at":"2018-09-16T20:33:40Z","schema_name":"taxon","title":"Work","withdrawn":false,"description":"","details":{"internal_name":"Work","notes_for_editors":"","visible_to_departmental_editors":true},"phase":"live","links":{"root_taxon":[{"api_path":"/api/content/","base_path":"/","content_id":"f3bbdec2-0e62-4520-a7fd-6ffd5d36e03a","document_type":"homepage","locale":"en","public_updated_at":"2019-06-21T11:52:37Z","schema_name":"homepage","title":"GOV.UK homepage","withdrawn":false,"links":{},"api_url":"https://www.gov.uk/api/content/","web_url":"https://www.gov.uk/"}]},"api_url":"https://www.gov.uk/api/content/work","web_url":"https://www.gov.uk/work"}]},"api_url":"https://www.gov.uk/api/content/employment/working","web_url":"https://www.gov.uk/employment/working"}]},"api_url":"https://www.gov.uk/api/content/employment/working-state-pension","web_url":"https://www.gov.uk/employment/working-state-pension"},{"api_path":"/api/content/employment/workplace-personal-pensions","base_path":"/employment/workplace-personal-pensions","content_id":"a99fc39c-997a-4b1a-9e6d-8cf63a3100be","document_type":"taxon","locale":"en","public_updated_at":"2018-08-22T11:08:23Z","schema_name":"taxon","title":"Workplace and personal pensions","withdrawn":false,"description":"Includes automatic enrolment, lost pensions and planning for retirement","details":{"internal_name":"Workplace and personal pensions [M]","notes_for_editors":"","visible_to_departmental_editors":false},"phase":"live","links":{"parent_taxons":[{"api_path":"/api/content/employment/working","base_path":"/employment/working","content_id":"092348a4-b896-4f8f-a0dc-e6d4605a4904","document_type":"taxon","locale":"en","public_updated_at":"2018-08-22T11:08:23Z","schema_name":"taxon","title":"Working, jobs and pensions","withdrawn":false,"description":"Includes holidays and finding a job","details":{"internal_name":"Working, jobs and pensions [M] (merged, level 2, work theme)","notes_for_editors":"","visible_to_departmental_editors":false},"phase":"live","links":{"parent_taxons":[{"api_path":"/api/content/work","base_path":"/work","content_id":"d0f1e5a3-c8f4-4780-8678-994f19104b21","document_type":"taxon","locale":"en","public_updated_at":"2018-09-16T20:33:40Z","schema_name":"taxon","title":"Work","withdrawn":false,"description":"","details":{"internal_name":"Work","notes_for_editors":"","visible_to_departmental_editors":true},"phase":"live","links":{"root_taxon":[{"api_path":"/api/content/","base_path":"/","content_id":"f3bbdec2-0e62-4520-a7fd-6ffd5d36e03a","document_type":"homepage","locale":"en","public_updated_at":"2019-06-21T11:52:37Z","schema_name":"homepage","title":"GOV.UK homepage","withdrawn":false,"links":{},"api_url":"https://www.gov.uk/api/content/","web_url":"https://www.gov.uk/"}]},"api_url":"https://www.gov.uk/api/content/work","web_url":"https://www.gov.uk/work"}]},"api_url":"https://www.gov.uk/api/content/employment/working","web_url":"https://www.gov.uk/employment/working"}]},"api_url":"https://www.gov.uk/api/content/employment/workplace-personal-pensions","web_url":"https://www.gov.uk/employment/workplace-personal-pensions"}],"organisations":[{"analytics_identifier":"D10","api_path":"/api/content/government/organisations/department-for-work-pensions","base_path":"/government/organisations/department-for-work-pensions","content_id":"b548a09f-8b35-4104-89f4-f1a40bf3136d","document_type":"organisation","locale":"en","schema_name":"organisation","title":"Department for Work and Pensions","withdrawn":false,"details":{"logo":{"formatted_title":"Department\u003cbr/\u003efor Work \u0026amp; \u003cbr/\u003ePensions","crest":"single-identity"},"brand":"department-for-work-pensions","default_news_image":{"url":"https://assets.publishing.service.gov.uk/government/uploads/system/uploads/default_news_organisation_image_data/file/35/s300_dwp-caxton-house-logo-960.jpg","high_resolution_url":"https://assets.publishing.service.gov.uk/government/uploads/system/uploads/default_news_organisation_image_data/file/35/s960_dwp-caxton-house-logo-960.jpg"}},"links":{},"api_url":"https://www.gov.uk/api/content/government/organisations/department-for-work-pensions","web_url":"https://www.gov.uk/government/organisations/department-for-work-pensions"}],"people":[{"api_path":"/api/content/government/people/amber-rudd","base_path":"/government/people/amber-rudd","content_id":"85395ec8-c0f1-11e4-8223-005056011aef","document_type":"person","locale":"en","public_updated_at":"2019-11-06T00:11:09Z","schema_name":"person","title":"The Rt Hon Amber Rudd","withdrawn":false,"links":{},"api_url":"https://www.gov.uk/api/content/government/people/amber-rudd","web_url":"https://www.gov.uk/government/people/amber-rudd"}],"primary_publishing_organisation":[{"analytics_identifier":"D10","api_path":"/api/content/government/organisations/department-for-work-pensions","base_path":"/government/organisations/department-for-work-pensions","content_id":"b548a09f-8b35-4104-89f4-f1a40bf3136d","document_type":"organisation","locale":"en","schema_name":"organisation","title":"Department for Work and Pensions","withdrawn":false,"details":{"logo":{"formatted_title":"Department\u003cbr/\u003efor Work \u0026amp; \u003cbr/\u003ePensions","crest":"single-identity"},"brand":"department-for-work-pensions","default_news_image":{"url":"https://assets.publishing.service.gov.uk/government/uploads/system/uploads/default_news_organisation_image_data/file/35/s300_dwp-caxton-house-logo-960.jpg","high_resolution_url":"https://assets.publishing.service.gov.uk/government/uploads/system/uploads/default_news_organisation_image_data/file/35/s960_dwp-caxton-house-logo-960.jpg"}},"links":{},"api_url":"https://www.gov.uk/api/content/government/organisations/department-for-work-pensions","web_url":"https://www.gov.uk/government/organisations/department-for-work-pensions"}],"roles":[{"api_path":"/api/content/government/ministers/secretary-of-state-for-work-and-pensions","base_path":"/government/ministers/secretary-of-state-for-work-and-pensions","content_id":"845e6272-c0f1-11e4-8223-005056011aef","document_type":"ministerial_role","locale":"en","public_updated_at":"2018-01-10T10:52:23Z","schema_name":"role","title":"Secretary of State for Work and Pensions","withdrawn":false,"details":{"body":"\u003cp\u003eThe Secretary of State has overall responsibility for the Department for Work and Pensions (\u003cabbr title=\"Department for Work and Pensions\"\u003eDWP\u003c/abbr\u003e). They have direct responsibility for departmental expenditure and departmental management.\u003c/p\u003e\n\n\u003cp\u003e\u003cabbr title=\"Department for Work and Pensions\"\u003eDWP\u003c/abbr\u003e is responsible for the administration of the State Pension and working age benefits system, providing support to:\u003c/p\u003e\n\n\u003cul\u003e\n  \u003cli\u003epeople of working age\u003c/li\u003e\n  \u003cli\u003eemployers\u003c/li\u003e\n  \u003cli\u003epensioners\u003c/li\u003e\n  \u003cli\u003efamilies and children\u003c/li\u003e\n  \u003cli\u003edisabled people\u003c/li\u003e\n\u003c/ul\u003e\n\n"},"links":{},"api_url":"https://www.gov.uk/api/content/government/ministers/secretary-of-state-for-work-and-pensions","web_url":"https://www.gov.uk/government/ministers/secretary-of-state-for-work-and-pensions"}],"available_translations":[{"title":"Green light for dashboards in 2019 puts pension savers in the driving seat","public_updated_at":"2019-04-04T12:40:46Z","document_type":"press_release","schema_name":"news_article","base_path":"/government/news/green-light-for-dashboards-in-2019-puts-pension-savers-in-the-driving-seat","api_path":"/api/content/government/news/green-light-for-dashboards-in-2019-puts-pension-savers-in-the-driving-seat","withdrawn":false,"content_id":"7d33a106-40f3-4309-b823-ad88e130623e","locale":"en","api_url":"https://www.gov.uk/api/content/government/news/green-light-for-dashboards-in-2019-puts-pension-savers-in-the-driving-seat","web_url":"https://www.gov.uk/government/news/green-light-for-dashboards-in-2019-puts-pension-savers-in-the-driving-seat","links":{}}]},"description":"Pensions dashboards which will revolutionise retirement planning have been given the green light by the Work and Pensions Secretary today - with initial industry models expected this year.","details":{"body":"\u003cp\u003eAmber Rudd unveiled proposals today (4 April) to support industry to deliver free, user-friendly services showing people their pensions information online.\u003c/p\u003e\n\n\u003cp\u003eSavers will be in the driving seat with all the facts and figures about their pensions and potential retirement income at their fingertips in one place for the first time - on smartphones, tablets and computers.\u003c/p\u003e\n\n\u003cp\u003eWork and Pensions Secretary Amber Rudd said:\u003c/p\u003e\n\n\u003cblockquote\u003e\n  \u003cp\u003eWith record numbers saving for retirement as a result of our revolutionary reforms, it’s more important than ever that people understand their pensions and prepare for financial security in later life.\u003c/p\u003e\n\n  \u003cp class=\"last-child\"\u003eDashboards have the potential to transform the way we all think about and plan for retirement, providing clear and simple information regarding pension savings in one place online. I’m looking forward to seeing the first industry dashboards later this year.\u003c/p\u003e\n\u003c/blockquote\u003e\n\n\u003cp\u003eKey details of the government’s plans, published today in its response to a consultation on dashboards, include:\u003c/p\u003e\n\n\u003cul\u003e\n  \u003cli\u003e\n    \u003cp\u003ea commitment to bring forward legislation at the earliest opportunity to compel all pension providers to make consumers’ data available to them through a dashboard\u003c/p\u003e\n  \u003c/li\u003e\n  \u003cli\u003e\n    \u003cp\u003ean expectation that the majority of schemes will be ready to ‘go live’ with their data within a 3 to 4 year window\u003c/p\u003e\n  \u003c/li\u003e\n  \u003cli\u003e\n    \u003cp\u003econfirmation that State Pension information will be included as soon as possible\u003c/p\u003e\n  \u003c/li\u003e\n  \u003cli\u003e\n    \u003cp\u003edashboards will help to reconnect people with ‘lost’ pension pots, benefitting savers and providers\u003c/p\u003e\n  \u003c/li\u003e\n\u003c/ul\u003e\n\n\u003cp\u003eMinisters support the development of multiple industry-led dashboards displaying the same basic information. Industry have told government that initial models will be developed and tested from this year. A non-commercial dashboard will be delivered and overseen by the new Single Financial Guidance Body (\u003cabbr title=\"Single Financial Guidance Body\"\u003eSFGB\u003c/abbr\u003e).\u003c/p\u003e\n\n\u003cp\u003eAn industry delivery group will be brought together by the \u003cabbr title=\"Single Financial Guidance Body\"\u003eSFGB\u003c/abbr\u003e which will set out a clear timetable and roadmap to drive progress towards fully operational dashboards, setting standards and ensuring security to protect users and their information.\u003c/p\u003e\n\n\u003cp\u003eJohn Govett, \u003cabbr title=\"Single Financial Guidance Body\"\u003eSFGB\u003c/abbr\u003e Chief Executive, said:\u003c/p\u003e\n\n\u003cblockquote\u003e\n  \u003cp class=\"last-child\"\u003eWe are delighted to be working with the Department for Work and Pensions and the whole pensions industry throughout 2019 to take forward the pensions dashboards.\u003c/p\u003e\n\u003c/blockquote\u003e\n\n\u003cblockquote\u003e\n  \u003cp class=\"last-child\"\u003eOur vision is everyone making the most of their money and pensions. A big part of this is equipping and empowering people to engage with their pensions, often the biggest financial investment they will make. The new pensions dashboards will play a crucial role in this, helping people make decisions about their money and pensions with confidence, so they can enjoy greater financial wellbeing throughout their lifetimes.\u003c/p\u003e\n\u003c/blockquote\u003e\n\n\u003cp\u003eYvonne Braun, Director of Long-term Savings and Protection Policy at the Association of British Insurers (\u003cabbr title=\"Association of British Insurers\"\u003eABI\u003c/abbr\u003e), said:\u003c/p\u003e\n\n\u003cp\u003e“The digital retirement revolution is here at last. All the pieces are being put in place to deliver the easy access to retirement information everybody needs and that the pensions industry is so keen to deliver.\u003c/p\u003e\n\n\u003cp\u003e“The \u003cabbr title=\"Association of British Insurers\"\u003eABI\u003c/abbr\u003e, leading a cross-industry group of pension providers and schemes, has already put years of work into making dashboards happen and we can’t wait to see these vital services in action. We’re delighted to see the government committing to the necessary legislation and will continue to play our part in making dashboards a reality.\u003c/p\u003e\n\n\u003cp\u003eNigel Peaple, Director of Policy and Research, Pensions and Lifetime Savings Association, said:\u003c/p\u003e\n\n\u003cblockquote\u003e\n  \u003cp class=\"last-child\"\u003ePensions dashboards will be a significant step forward in helping savers plan their retirement income. We fully support the government’s recommendation that the initial phase should involve a non-commercial dashboard hosted by the \u003cabbr title=\"Single Financial Guidance Body\"\u003eSFGB\u003c/abbr\u003e and that the State Pension should be included as soon as possible.\u003c/p\u003e\n\u003c/blockquote\u003e\n\n\u003cblockquote\u003e\n  \u003cp class=\"last-child\"\u003ePreparing the sector for connection to pensions dashboards will be a major undertaking and one that we stand ready to support. The government is right to acknowledge that connecting the majority of schemes may take 3 or 4 years. But the government is also right to urge the pensions industry to act quickly, in 2019, to enhance the quality of their data, and to support the \u003cabbr title=\"Single Financial Guidance Body\"\u003eSFGB\u003c/abbr\u003e in developing appropriate data standards. We look forward to working with the \u003cabbr title=\"Single Financial Guidance Body\"\u003eSFGB\u003c/abbr\u003e, the pensions industry and consumer groups to deliver this important project.\u003c/p\u003e\n\u003c/blockquote\u003e\n\n\u003cp\u003eGareth Shaw, Head of Money, Which?, said:\u003c/p\u003e\n\n\u003cblockquote\u003e\n  \u003cp class=\"last-child\"\u003eIt is encouraging to see the important recognition that all schemes must be included in dashboards, allowing consumers to finally see all of their pots in one place - so the government must introduce legislation to ensure this is achieved.\u003c/p\u003e\n\u003c/blockquote\u003e\n\n\u003cblockquote\u003e\n  \u003cp class=\"last-child\"\u003eWe welcome the crucial commitment to including the state pension. Dashboards won’t be complete without this vital component so it must be included at the earliest opportunity. Every dashboard must display all the important information consumers need in a clear and accessible way, allowing them to easily understand their pension savings and the costs involved. The delivery group has been tasked with some massive decisions that will determine the dashboards’ success - so we must see a clear commitment to delivering consumer-friendly tools within a swift timeframe.\u003c/p\u003e\n\u003c/blockquote\u003e\n\n\u003cdiv class=\"call-to-action\"\u003e\n\u003cp\u003eRead the \u003ca href=\"https://www.gov.uk/government/consultations/pensions-dashboards-feasibility-report-and-consultation\"\u003egovernment’s response to the pensions dashboards consultation\u003c/a\u003e.\u003c/p\u003e\n\u003c/div\u003e\n\n\u003ch2 id=\"contact-press-office\"\u003eContact Press Office\u003c/h2\u003e\n\n\u003cp\u003eMedia enquiries for this press release – 020 3267  5120\u003c/p\u003e\n\n\u003cdiv id=\"contact_df0a78d2-6122-46ac-8014-6f8c5e0b8d3f\" class=\"contact postal-address\"\u003e\n  \u003cdiv class=\"content\"\u003e\n    \u003ch3\u003ePress Office\u003c/h3\u003e\n    \u003cdiv class=\"vcard contact-inner\"\u003e\n    \n      \u003cp class=\"adr\"\u003e\n\u003cspan class=\"street-address\"\u003eCaxton House\n\u003cbr\u003e\nTothill Street\u003c/span\u003e\u003cbr\u003e\n\u003cspan class=\"locality\"\u003eLondon\u003c/span\u003e\u003cbr\u003e\n\u003cspan class=\"postal-code\"\u003eSW1H 9NA\u003c/span\u003e\n\u003c/p\u003e\n\n    \n    \n      \u003cdiv class=\"email-url-number\"\u003e\n      \n      \n      \n        \u003cp class=\"tel\"\u003e\n          \u003cspan class=\"type\"\u003eLondon Press Office (national media and London area enquiries only – not questions about personal claims)\u003c/span\u003e\n          020 3267 5144\n        \u003c/p\u003e\n      \n        \u003cp class=\"tel\"\u003e\n          \u003cspan class=\"type\"\u003eOut-of-hours (journalists only)\u003c/span\u003e\n          07623 928 975\n        \u003c/p\u003e\n      \n        \u003cp class=\"tel\"\u003e\n          \u003cspan class=\"type\"\u003eEngland and Wales (local media enquiries)\u003c/span\u003e\n          029 20 586 then 097 or 098 or 099\n        \u003c/p\u003e\n      \n        \u003cp class=\"tel\"\u003e\n          \u003cspan class=\"type\"\u003eScotland (local media enquiries)\u003c/span\u003e\n          0131 310 1122\n        \u003c/p\u003e\n      \n      \u003c/div\u003e\n    \n    \n    \u003c/div\u003e\n  \u003c/div\u003e\n\u003c/div\u003e\n\n\u003cp\u003eFollow \u003cabbr title=\"Department for Work and Pensions\"\u003eDWP\u003c/abbr\u003e on:\u003c/p\u003e\n\n\u003cul\u003e\n  \u003cli\u003e\u003ca rel=\"external\" href=\"https://www.twitter.com/dwppressoffice\"\u003eTwitter\u003c/a\u003e\u003c/li\u003e\n  \u003cli\u003e\u003ca rel=\"external\" href=\"https://www.facebook.com/dwp\"\u003eFacebook\u003c/a\u003e\u003c/li\u003e\n  \u003cli\u003e\u003ca rel=\"external\" href=\"https://www.linkedin.com/company/dwp\"\u003eLinkedIn\u003c/a\u003e\u003c/li\u003e\n  \u003cli\u003e\u003ca rel=\"external\" href=\"https://www.youtube.com/dwp\"\u003eYouTube\u003c/a\u003e\u003c/li\u003e\n\u003c/ul\u003e\n\n","change_history":[{"note":"First published.","public_timestamp":"2019-04-04T12:32:17.071Z"}]}}